kable_python_flask/__init__.py
kable_python_flask/external.py
kable_python_flask/server.py
kable_python_flask-4.0.1.dist-info/LICENSE
kable_python_flask-4.0.1.dist-info/METADATA
kable_python_flask-4.0.1.dist-info/WHEEL
kable_python_flask-4.0.1.dist-info/top_level.txt
kable_python_flask-4.0.1.dist-info/RECORD
