Metadata-Version: 2.1
Name: kable-python-flask
Version: 4.0.1
Summary: Kable Python Flask SDK
Home-page: https://kable.io
Author: Kable
Author-email: contact@kable.io
Project-URL: Bug Tracker, https://github.com/Kable-io/kable-python-flask-sdk/issues
Classifier: Programming Language :: Python :: 3
Classifier: License :: OSI Approved :: MIT License
Classifier: Operating System :: OS Independent
Requires-Python: >=3.6
License-File: LICENSE
Requires-Dist: Flask
Requires-Dist: requests
Requires-Dist: cachetools
